ezyagent/__init__.py
ezyagent/core/__init__.py
ezyagent/core/_types/__init__.py
ezyagent/core/_types/_huggingface.py
ezyagent/core/agents/__init__.py
ezyagent/core/agents/agent.py
ezyagent/core/agents/agentpool.py
ezyagent/core/agents/base.py
ezyagent/core/agents/models.py
ezyagent/core/agents/schemas.py
ezyagent/core/agents/variations/__init__.py
ezyagent/core/agents/variations/llamaindex_react_agent.py
ezyagent/core/memory/__init__.py
ezyagent/core/memory/base.py
ezyagent/core/memory/manager.py
ezyagent/core/memory/simple.py
ezyagent/core/providers/__init__.py
ezyagent/core/providers/base.py
ezyagent/core/providers/config.py
ezyagent/core/providers/factories/__init__.py
ezyagent/core/providers/factories/huggingface.py
ezyagent/core/providers/factories/ollama.py
ezyagent/core/providers/factories/openai.py
ezyagent/core/providers/openai_client_vars.py
ezyagent/core/providers/registry.py
ezyagent/core/providers/setup.py
ezyagent/core/tools/__init__.py
ezyagent/core/tools/base.py
ezyagent/core/tools/builtin.py
ezyagent/core/tools/manager.py
ezyagent/core/tools/utils.py
ezyagent/customs/__init__.py
ezyagent/customs/main.py
ezyagent/examples/__init__.py
ezyagent/examples/agent_example.py
ezyagent/examples/agent_pool.py
ezyagent/examples/agents_with_persona.py
ezyagent/examples/async_agent_example.py
ezyagent/examples/async_agent_tool_example.py
ezyagent/examples/huggingface_provider_example.py
ezyagent/examples/logging_example.py
ezyagent/examples/memory_example.py
ezyagent/examples/ollama_provider_example.py
ezyagent/examples/sample_tool_call.py
ezyagent/examples/tools_example.py
ezyagent/logging/__init__.py
ezyagent/logging/formatters.py
ezyagent/logging/handlers.py
ezyagent/logging/logger.py
ezyagent/logging/monitors.py
ezyagent/utils/__init__.py
ezyagent/utils/errors.py
ezyagent/utils/helpers.py
ezyagent/utils/validation.py
ezyagent-0.0.13.dist-info/METADATA
ezyagent-0.0.13.dist-info/WHEEL
ezyagent-0.0.13.dist-info/RECORD
